[
    {
        "title": "Tambon Huai Sat Yai, Thailand",
        "distance": "368 km away",
        "stay": "8 nights stay",
        "total": "50771 total before taxes",
        "url": "https://a0.muscache.com/im/pictures/miso/Hosting-1281034989788919425/original/18c6bb05-c2d4-49ba-9df4-36d11ca70b6d.jpeg?im_w=720"
    },
    {
        "title": "Jibhi, India",
        "distance": "246 km away",
        "stay": "7 nights stay",
        "total": "18795 total before taxes",
        "url": "https://a0.muscache.com/im/pictures/miso/Hosting-804959254707180514/original/fdba3a5f-da62-4b50-83ea-517639ba1385.jpeg?im_w=720"
    },
    {
        "title": "Hua Hin, Thailand",
        "distance": "295 km away",
        "stay": "4 nights stay",
        "total": "53446 total before taxes",
        "url": "https://a0.muscache.com/im/pictures/miso/Hosting-53163431/original/b795749c-0d45-48b9-b458-120dbfba9794.jpeg?im_w=720"
    },
    {
        "title": "\u0e23\u0e2d\u0e1a\u0e40\u0e27\u0e35\u0e22\u0e07, Thailand",
        "distance": "11 km away",
        "stay": "10 nights stay",
        "total": "11330 total before taxes",
        "url": "https://a0.muscache.com/im/pictures/ec7a55ab-31d6-483b-9386-ad6a213d94db.jpg?im_w=720"
    },
    {
        "title": "Phong Th\u1ed5 District, Vietnam",
        "distance": "17 km away",
        "stay": "3 nights stay",
        "total": "54403 total before taxes",
        "url": "https://a0.muscache.com/im/pictures/8fb5846e-bb22-43d0-97f7-8a53aa86880f.jpg?im_w=720"
    },
    {
        "title": "\u0e02\u0e2d\u0e19\u0e41\u0e01\u0e48\u0e19, Thailand",
        "distance": "226 km away",
        "stay": "5 nights stay",
        "total": "50814 total before taxes",
        "url": "https://a0.muscache.com/im/pictures/8b6ec929-288c-47b3-93c6-cf92d5694efd.jpg?im_w=720"
    },
    {
        "title": "Baybulak, Kazakhstan",
        "distance": "108 km away",
        "stay": "7 nights stay",
        "total": "13445 total before taxes",
        "url": "https://a0.muscache.com/im/pictures/hosting/Hosting-41949744/original/a2af90c2-e7d4-4c88-908c-b8bfe8891ffa.jpeg?im_w=720"
    },
    {
        "title": "Palshet, India",
        "distance": "198 km away",
        "stay": "10 nights stay",
        "total": "67380 total before taxes",
        "url": "https://a0.muscache.com/im/pictures/3cfab2a2-cd73-4e67-8e39-ef74d5b50cf2.jpg?im_w=720"
    },
    {
        "title": "Taling Ngam, Thailand",
        "distance": "218 km away",
        "stay": "3 nights stay",
        "total": "51398 total before taxes",
        "url": "https://a0.muscache.com/im/pictures/hosting/Hosting-U3RheVN1cHBseUxpc3Rpbmc6MTIzNzk4ODY3NTAyODM5MDI0MA%3D%3D/original/f17583e4-c9ed-442d-b67b-d0e66842cabc.jpeg?im_w=720"
    },
    {
        "title": "Idukki, India",
        "distance": "88 km away",
        "stay": "4 nights stay",
        "total": "25006 total before taxes",
        "url": "https://a0.muscache.com/im/pictures/7be27856-9ea9-424b-81ae-7672e37a5229.jpg?im_w=720"
    },
    {
        "title": "Doddanahalli, India",
        "distance": "459 km away",
        "stay": "4 nights stay",
        "total": "36799 total before taxes",
        "url": "https://a0.muscache.com/im/pictures/miso/Hosting-592295535437322987/original/053fb681-7bcd-4629-b33e-c14e22d2ebe9.jpeg?im_w=720"
    },
    {
        "title": "Mueang Ngai, Thailand",
        "distance": "444 km away",
        "stay": "4 nights stay",
        "total": "52484 total before taxes",
        "url": "https://a0.muscache.com/im/pictures/miso/Hosting-1085859069128606931/original/3a777d24-c12f-408b-9b03-8f8735c5cae2.jpeg?im_w=720"
    },
    {
        "title": "Palshet, India",
        "distance": "268 km away",
        "stay": "4 nights stay",
        "total": "74430 total before taxes",
        "url": "https://a0.muscache.com/im/pictures/miso/Hosting-29375910/original/ec1c796c-1c31-4249-afc3-963cbde91268.jpeg?im_w=720"
    },
    {
        "title": "Mandrem, India",
        "distance": "193 km away",
        "stay": "5 nights stay",
        "total": "13863 total before taxes",
        "url": "https://a0.muscache.com/im/pictures/miso/Hosting-1286208323180296244/original/59132e17-641d-468c-88a6-289952403d08.jpeg?im_w=720"
    },
    {
        "title": "Mueang Chiang Mai District, Thailand",
        "distance": "481 km away",
        "stay": "2 nights stay",
        "total": "38496 total before taxes",
        "url": "https://a0.muscache.com/im/pictures/a77b1c22-96cf-4ac0-a430-b5572c15df8a.jpg?im_w=720"
    },
    {
        "title": "Mandrem, India",
        "distance": "130 km away",
        "stay": "8 nights stay",
        "total": "40103 total before taxes",
        "url": "https://a0.muscache.com/im/pictures/miso/Hosting-1286300709435518458/original/57de8a27-7d06-4b24-bb14-8f10bec6efd3.jpeg?im_w=720"
    },
    {
        "title": "Jibhi, India",
        "distance": "304 km away",
        "stay": "2 nights stay",
        "total": "70106 total before taxes",
        "url": "https://a0.muscache.com/im/pictures/1e9c33fb-fb80-4292-ae35-0675de292bf4.jpg?im_w=720"
    },
    {
        "title": "Kodaikanal, India",
        "distance": "403 km away",
        "stay": "8 nights stay",
        "total": "56102 total before taxes",
        "url": "https://a0.muscache.com/im/pictures/hosting/Hosting-1127305222505894362/original/b0a73652-b889-4566-8332-1451fba27294.jpeg?im_w=720"
    },
    {
        "title": "Naggar, India",
        "distance": "205 km away",
        "stay": "5 nights stay",
        "total": "40834 total before taxes",
        "url": "https://a0.muscache.com/im/pictures/miso/Hosting-586640580469243869/original/3b9932e6-7809-4222-b525-6205cb910302.jpeg?im_w=720"
    },
    {
        "title": "Kamshet, India",
        "distance": "238 km away",
        "stay": "9 nights stay",
        "total": "65873 total before taxes",
        "url": "https://a0.muscache.com/im/pictures/abb31739-0262-4004-8453-1cb393c01505.jpg?im_w=720"
    },
    {
        "title": "IN, India",
        "distance": "333 km away",
        "stay": "9 nights stay",
        "total": "71689 total before taxes",
        "url": "https://a0.muscache.com/im/pictures/6b0a1b50-e50a-4766-adbe-e96b9e47bb2c.jpg?im_w=720"
    },
    {
        "title": "Kozhikode, India",
        "distance": "71 km away",
        "stay": "8 nights stay",
        "total": "36914 total before taxes",
        "url": "https://a0.muscache.com/im/pictures/0d9dc90c-0330-46a8-921b-16375a3092df.jpg?im_w=720"
    },
    {
        "title": "Lonavla, India",
        "distance": "217 km away",
        "stay": "8 nights stay",
        "total": "50330 total before taxes",
        "url": "https://a0.muscache.com/im/pictures/da51690b-d548-4947-9f69-eda9f1cfd3f7.jpg?im_w=720"
    },
    {
        "title": "Tambon San Pa Yang, Thailand",
        "distance": "246 km away",
        "stay": "3 nights stay",
        "total": "18362 total before taxes",
        "url": "https://a0.muscache.com/im/pictures/ae441b77-ba8a-4cb3-b4b1-647b6376d776.jpg?im_w=720"
    },
    {
        "title": "New Delhi, India",
        "distance": "236 km away",
        "stay": "3 nights stay",
        "total": "27878 total before taxes",
        "url": "https://a0.muscache.com/im/pictures/0dc20155-bfd2-4f5a-b09a-9303b8edb0e0.jpg?im_w=720"
    },
    {
        "title": "Tambon Su Thep, Thailand",
        "distance": "31 km away",
        "stay": "2 nights stay",
        "total": "15217 total before taxes",
        "url": "https://a0.muscache.com/im/pictures/7998c806-21f2-48a4-9f1f-b877236d6ed8.jpg?im_w=720"
    },
    {
        "title": "Mussoorie, India",
        "distance": "489 km away",
        "stay": "6 nights stay",
        "total": "17050 total before taxes",
        "url": "https://a0.muscache.com/im/pictures/miso/Hosting-1081746146834245960/original/08a87fe5-5831-47e5-bd8c-9d2c9ed37ba7.jpeg?im_w=720"
    },
    {
        "title": "Bangkok, Thailand",
        "distance": "361 km away",
        "stay": "6 nights stay",
        "total": "25459 total before taxes",
        "url": "https://a0.muscache.com/im/pictures/9117718f-3068-4271-b07f-7aac317f6fb6.jpg?im_w=720"
    },
    {
        "title": "Dalhousie, India",
        "distance": "478 km away",
        "stay": "9 nights stay",
        "total": "54747 total before taxes",
        "url": "https://a0.muscache.com/im/pictures/miso/Hosting-1308451056848438354/original/d36dcd54-2bfd-4479-ba11-a93c09f4aca5.jpeg?im_w=720"
    },
    {
        "title": "Saikhola, India",
        "distance": "261 km away",
        "stay": "9 nights stay",
        "total": "15584 total before taxes",
        "url": "https://a0.muscache.com/im/pictures/hosting/Hosting-1102908865910671539/original/a0147702-cb7c-4b9d-b1a4-1672c77b709b.jpeg?im_w=720"
    },
    {
        "title": "Lak Si, Thailand",
        "distance": "211 km away",
        "stay": "2 nights stay",
        "total": "15908 total before taxes",
        "url": "https://a0.muscache.com/im/pictures/25d6a82f-2255-46c3-b446-a17235efb78b.jpg?im_w=720"
    },
    {
        "title": "Amphoe Mueang Chiang Mai, Thailand",
        "distance": "389 km away",
        "stay": "4 nights stay",
        "total": "50003 total before taxes",
        "url": "https://a0.muscache.com/im/pictures/miso/Hosting-22294070/original/fa947bdf-5ee5-48e6-bf31-21c9e512e895.jpeg?im_w=720"
    }
]